{"type":"morphism","name":"$\\AA^\\infty_\\QQ$ with double origin to $\\Spec \\QQ$","with":{"source":"AA-inf-QQ-double-origin","target":"Spec-QQ"},"adjectives":{"surjective":true,"quasi-separated":false,"closed":true,"of-finite-presentation":false,"quasi-compact":true,"semi-separated":false,"separated":false,"proper":false,"injective":false,"quasi-affine":false,"finite":false,"homeomorphism":false,"immersion":false,"affine":false,"closed-immersion":false,"open-immersion":false},"proofs":{"surjective":"The target consists of one point and the source is non-empty.","quasi-separated":"Denote the source by $X$ and $X_1, X_2 \\subset X$ the two copies of $\\AA^\\infty_\\QQ$. Now $\\Delta_{X/\\QQ}(X_1 \\times X_2) = \\AA^\\infty_\\QQ \\setminus \\{ 0 \\}$ is not quasi-compact.","closed":"The target has discrete topology.","of-finite-presentation":{"type":"morphism","theorem":"fp-of-lfp-qc-qsp","subject":"AA-inf-QQ-double-origin-to-Spec-QQ","converse":true,"negated":{"path":"","adjective":"of-finite-presentation"}},"quasi-compact":{"type":"morphism","theorem":"qc-of-src-qc","subject":"AA-inf-QQ-double-origin-to-Spec-QQ"},"semi-separated":{"type":"morphism","theorem":"qsp-of-ssp","subject":"AA-inf-QQ-double-origin-to-Spec-QQ","negated":{"path":"","adjective":"semi-separated"}},"separated":{"type":"morphism","theorem":"ssp-of-sp","subject":"AA-inf-QQ-double-origin-to-Spec-QQ","negated":{"path":"","adjective":"separated"}},"proper":{"type":"morphism","theorem":"pr-of-ft-uc-sp","subject":"AA-inf-QQ-double-origin-to-Spec-QQ","converse":true,"negated":{"path":"","adjective":"proper"}},"injective":{"type":"morphism","theorem":"sp-of-inj","subject":"AA-inf-QQ-double-origin-to-Spec-QQ","negated":{"path":"","adjective":"injective"}},"quasi-affine":{"type":"morphism","theorem":"sp-of-qaf","subject":"AA-inf-QQ-double-origin-to-Spec-QQ","negated":{"path":"","adjective":"quasi-affine"}},"finite":{"type":"morphism","theorem":"fn-of-pr-af","subject":"AA-inf-QQ-double-origin-to-Spec-QQ","converse":true,"negated":{"path":"","adjective":"finite"}},"homeomorphism":{"type":"morphism","theorem":"inj-of-hm","subject":"AA-inf-QQ-double-origin-to-Spec-QQ","negated":{"path":"","adjective":"homeomorphism"}},"immersion":{"type":"morphism","theorem":"inj-of-imm","subject":"AA-inf-QQ-double-origin-to-Spec-QQ","negated":{"path":"","adjective":"immersion"}},"affine":{"type":"morphism","theorem":"qaf-of-af","subject":"AA-inf-QQ-double-origin-to-Spec-QQ","negated":{"path":"","adjective":"affine"}},"closed-immersion":{"type":"morphism","theorem":"fn-of-ci","subject":"AA-inf-QQ-double-origin-to-Spec-QQ","negated":{"path":"","adjective":"closed-immersion"}},"open-immersion":{"type":"morphism","theorem":"imm-of-oi","subject":"AA-inf-QQ-double-origin-to-Spec-QQ","negated":{"path":"","adjective":"open-immersion"}}},"description":"The natural morphism from $\\AA^\\infty_\\QQ$ with double origin to $\\Spec \\QQ$."}