{"type":"scheme","name":"$\\Spec \\RR[x, y] / (x^2 + y^2)$","adjectives":{"affine":true,"quasi-affine":true,"quasi-compact":true,"separated":true,"semi-separated":true,"quasi-separated":true},"description":"The scheme $\\Spec \\RR[x, y] / (x^2 + y^2)$.","proofs":{"quasi-affine":{"type":"scheme","theorem":"qaf-of-af","subject":"Spec-RR-x2-y2"},"quasi-compact":{"type":"scheme","theorem":"qc-of-qaf","subject":"Spec-RR-x2-y2"},"separated":{"type":"scheme","theorem":"sp-of-qaf","subject":"Spec-RR-x2-y2"},"semi-separated":{"type":"scheme","theorem":"ssp-of-sp","subject":"Spec-RR-x2-y2"},"quasi-separated":{"type":"scheme","theorem":"qsp-of-ssp","subject":"Spec-RR-x2-y2"}}}